{
    "15": [
        29,
        0,
        0
    ],
    "16": [
        37,
        23,
        10
    ],
    "17": [
        33,
        24,
        7
    ],
    "18": [
        18,
        23,
        5
    ],
    "19": [
        34,
        25,
        7
    ],
    "20": [
        43,
        30,
        3
    ],
    "S15": [
        11,
        0,
        0
    ],
    "S16": [
        5,
        2,
        0
    ],
    "S17": [
        2,
        6,
        0
    ],
    "S18": [
        2,
        0,
        0
    ],
    "S19": [
        4,
        4,
        2
    ],
    "S20": [
        4,
        3,
        1
    ]
}